Metadata-Version: 2.0
Name: tutorial-package-jelena
Version: 0.0.1
Summary: An demonstration of how to create and publish python packages
Home-page: UNKNOWN
Author: Jelena Chuklina
Author-email: UNKNOWN
License: BSD
Platform: UNKNOWN
